knox/__init__.py
knox/admin.py
knox/auth.py
knox/crypto.py
knox/models.py
knox/serializers.py
knox/settings.py
knox/signals.py
knox/urls.py
knox/views.py
knox/migrations/__init__.py
django_knox_for-0.0.2.dist-info/METADATA
django_knox_for-0.0.2.dist-info/WHEEL
django_knox_for-0.0.2.dist-info/top_level.txt
django_knox_for-0.0.2.dist-info/RECORD
