Metadata-Version: 2.1
Name: django-knox-for
Version: 0.0.2
Summary: django-knox-for
Home-page: UNKNOWN
Author: Tordoir Julien
Author-email: <jt.tordoir@gmail.com>
License: UNKNOWN
Keywords: django,djangorestframework,django-knox-for
Platform: UNKNOWN
Classifier: Development Status :: 3 - Alpha
Classifier: Intended Audience :: Education
Classifier: Programming Language :: Python :: 2
Classifier: Programming Language :: Python :: 3
Classifier: Operating System :: MacOS :: MacOS X
Classifier: Operating System :: Microsoft :: Windows
